LICENSE
MANIFEST.in
README.rst
requirements.txt
setup.py
helga_lingo/__init__.py
helga_lingo/plugin.py
helga_lingo.egg-info/PKG-INFO
helga_lingo.egg-info/SOURCES.txt
helga_lingo.egg-info/dependency_links.txt
helga_lingo.egg-info/entry_points.txt
helga_lingo.egg-info/requires.txt
helga_lingo.egg-info/top_level.txt
helga_lingo.egg-info/zip-safe
tests/__init__.py
tests/test_lingo.py