Metadata-Version: 1.1
Name: helga-lingo
Version: 1.0.7
Summary: Define words from urbandictionary.com
Home-page: https://github.com/narfman0/helga-lingo
Author: Jon Robison
Author-email: narfman0@gmail.com
License: LICENSE
Keywords: irc bot lingo urbandictionary urban dictionary ud
Platform: UNKNOWN
Classifier: Development Status :: 4 - Beta
Classifier: Topic :: Communications :: Chat :: Internet Relay Chat
Classifier: License :: OSI Approved :: GNU General Public License v3 (GPLv3)
Classifier: Operating System :: OS Independent
Classifier: Programming Language :: Python
Classifier: Topic :: Software Development :: Libraries :: Python Modules
Classifier: Topic :: Communications :: Chat :: Internet Relay Chat
